beautymatrix/__init__.py
beautymatrix/beautymatrix.py
beautymatrix-1.2.1.dist-info/METADATA
beautymatrix-1.2.1.dist-info/WHEEL
beautymatrix-1.2.1.dist-info/licenses/LICENSE
beautymatrix-1.2.1.dist-info/RECORD
