Metadata-Version: 2.4
Name: beautymatrix
Version: 1.2.1
Summary: A Python package to convert numpy matrices to beautiful formatted strings
Author: Rnarok
License: MIT
License-File: LICENSE
Keywords: beautymatrix,formatting,matrix,matrix to string,numpy
Requires-Python: >=3.10.0
Requires-Dist: numpy>=2.0.0
